{"assets/fonts/Comfortaa-Medium.ttf":["assets/fonts/Comfortaa-Medium.ttf"],"assets/fonts/Comfortaa-Regular.ttf":["assets/fonts/Comfortaa-Regular.ttf"],"assets/images/Alfa Cure.png":["assets/images/Alfa Cure.png"],"assets/images/CS certificate.jpeg":["assets/images/CS certificate.jpeg"],"assets/images/Clean_arch.jpg":["assets/images/Clean_arch.jpg"],"assets/images/Complete Flutter & Dart Development Course.jpg":["assets/images/Complete Flutter & Dart Development Course.jpg"],"assets/images/DEPI_Cert.jpg":["assets/images/DEPI_Cert.jpg"],"assets/images/DOCEngine.png":["assets/images/DOCEngine.png"],"assets/images/Dart.svg":["assets/images/Dart.svg"],"assets/images/Flutter Advanced Course Bloc and MVVM Pattern.jpg":["assets/images/Flutter Advanced Course Bloc and MVVM Pattern.jpg"],"assets/images/GitHub.svg":["assets/images/GitHub.svg"],"assets/images/GitHubActions.svg":["assets/images/GitHubActions.svg"],"assets/images/HR Engine for employee.png":["assets/images/HR Engine for employee.png"],"assets/images/Insomnia.svg":["assets/images/Insomnia.svg"],"assets/images/Java.svg":["assets/images/Java.svg"],"assets/images/Mastering Flutter Responsive Adaptive UI Design.jpg":["assets/images/Mastering Flutter Responsive Adaptive UI Design.jpg"],"assets/images/PairExtraordinaire.png":["assets/images/PairExtraordinaire.png"],"assets/images/PetsAppLogo.png":["assets/images/PetsAppLogo.png"],"assets/images/Postman.svg":["assets/images/Postman.svg"],"assets/images/PullShark.png":["assets/images/PullShark.png"],"assets/images/QuickDraw_SkinTone1.png":["assets/images/QuickDraw_SkinTone1.png"],"assets/images/YOLO_Badge.png":["assets/images/YOLO_Badge.png"],"assets/images/animated.png":["assets/images/animated.png"],"assets/images/animated2.png":["assets/images/animated2.png"],"assets/images/animatedImage4.png":["assets/images/animatedImage4.png"],"assets/images/cookItLogo.png":["assets/images/cookItLogo.png"],"assets/images/craftscene_logo.png":["assets/images/craftscene_logo.png"],"assets/images/facebook.svg":["assets/images/facebook.svg"],"assets/images/farmedia_logo.png":["assets/images/farmedia_logo.png"],"assets/images/firebase.svg":["assets/images/firebase.svg"],"assets/images/flutter.svg":["assets/images/flutter.svg"],"assets/images/github-mark.svg":["assets/images/github-mark.svg"],"assets/images/github2.svg":["assets/images/github2.svg"],"assets/images/gmail.svg":["assets/images/gmail.svg"],"assets/images/google-cloud.svg":["assets/images/google-cloud.svg"],"assets/images/image-4775e472-ec59-4388-b070-6cd98c7ab97b.png":["assets/images/image-4775e472-ec59-4388-b070-6cd98c7ab97b.png"],"assets/images/instagram.svg":["assets/images/instagram.svg"],"assets/images/linkedin.svg":["assets/images/linkedin.svg"],"assets/images/profile.png":["assets/images/profile.png"],"assets/images/profile_pic1.png":["assets/images/profile_pic1.png"],"assets/images/profile_pic2.png":["assets/images/profile_pic2.png"],"assets/images/secondHome.png":["assets/images/secondHome.png"],"assets/images/twassol.png":["assets/images/twassol.png"],"assets/images/whatsapp.svg":["assets/images/whatsapp.svg"],"assets/images/youtube.svg":["assets/images/youtube.svg"],"packages/cupertino_icons/assets/CupertinoIcons.ttf":["packages/cupertino_icons/assets/CupertinoIcons.ttf"]}